adverse_event_app/__init__.py
adverse_event_app/action_items.py
adverse_event_app/admin.py
adverse_event_app/apps.py
adverse_event_app/baker_recipes.py
adverse_event_app/consents.py
adverse_event_app/list_data.py
adverse_event_app/models.py
adverse_event_app/visit_schedules.py
edc_adverse_event_app-1.0.5.dist-info/licenses/LICENSE
edc_adverse_event_app-1.0.5.dist-info/METADATA
edc_adverse_event_app-1.0.5.dist-info/WHEEL
edc_adverse_event_app-1.0.5.dist-info/top_level.txt
edc_adverse_event_app-1.0.5.dist-info/RECORD
