Metadata-Version: 2.4
Name: edc-adverse-event-app
Version: 1.0.5
Summary: Add your description here
License-Expression: GPL-3.0-or-later
Requires-Python: <3.14,>=3.12
License-File: LICENSE
Dynamic: license-file
